{
  "Big Bear TS": {
    "type": "Transfer Station",
    "swis": "36-AA-0417",
    "addr": "Holcomb Valley Rd off Hwy 18 (Big Bear Sanitary Landfill)",
    "city": "Big Bear City",
    "lat": 34.276,
    "lng": -116.844,
    "folder": "https://caiwoodgroup-my.sharepoint.com/personal/tamer_hassanein_caiwoodgroup_com/Documents/Athens/Environmental Facility Permits - Documents/Big Bear TS",
    "permits": [
      {
        "id": "p-big-bear-ts-01",
        "name": "Solid Waste Facility Permit",
        "agency": "CalRecycle / San Bernardino County (LEA)",
        "number": "36-AA-0417",
        "status": "active",
        "expires": null,
        "cycle": "5-year review",
        "area": "SWFP (SBC)",
        "doc": "https://caiwoodgroup-my.sharepoint.com/personal/tamer_hassanein_caiwoodgroup_com/Documents/Athens/Environmental Facility Permits - Documents/Big Bear TS/SWFP (SBC)"
      },
      {
        "id": "p-big-bear-ts-02",
        "name": "Hazardous Materials Business Plan (CUPA)",
        "agency": "San Bernardino County Fire / CUPA",
        "number": "EPA ID CAD982495632",
        "status": "active",
        "expires": null,
        "cycle": "annual",
        "area": "CUPA",
        "doc": "https://caiwoodgroup-my.sharepoint.com/personal/tamer_hassanein_caiwoodgroup_com/Documents/Athens/Environmental Facility Permits - Documents/Big Bear TS/CUPA"
      },
      {
        "id": "p-big-bear-ts-03",
        "name": "SPCC Plan",
        "agency": "US EPA (self-implementing)",
        "number": "",
        "status": "verify",
        "expires": null,
        "cycle": "5-year review",
        "area": "SPCC",
        "doc": "https://caiwoodgroup-my.sharepoint.com/personal/tamer_hassanein_caiwoodgroup_com/Documents/Athens/Environmental Facility Permits - Documents/Big Bear TS"
      }
    ],
    "leases": [],
    "checklist": []
  },
  "Morongo TS": {
    "type": "Transfer Station",
    "swis": "36-AA-0377",
    "addr": "Off State Highway 62 (Twentynine Palms Hwy), NE of Morongo Valley",
    "city": "Morongo Valley",
    "lat": 34.0464,
    "lng": -116.5803,
    "folder": "https://caiwoodgroup-my.sharepoint.com/personal/tamer_hassanein_caiwoodgroup_com/Documents/Athens/Environmental Facility Permits - Documents/Morongo TS",
    "permits": [
      {
        "id": "p-morongo-ts-01",
        "name": "Solid Waste Facility Permit",
        "agency": "San Bernardino County LEA / CalRecycle",
        "number": "36-AA-0377",
        "status": "active",
        "expires": null,
        "cycle": "",
        "area": "SWFP (SBC)",
        "doc": "https://caiwoodgroup-my.sharepoint.com/personal/tamer_hassanein_caiwoodgroup_com/Documents/Athens/Environmental Facility Permits - Documents/Morongo TS/SWFP (SBC)"
      },
      {
        "id": "p-morongo-ts-02",
        "name": "Hazardous Materials Business Plan (CUPA)",
        "agency": "San Bernardino County Fire / CUPA",
        "number": "",
        "status": "verify",
        "expires": null,
        "cycle": "",
        "area": "CUPA",
        "doc": "https://caiwoodgroup-my.sharepoint.com/personal/tamer_hassanein_caiwoodgroup_com/Documents/Athens/Environmental Facility Permits - Documents/Morongo TS/CUPA"
      }
    ],
    "leases": [],
    "checklist": []
  },
  "Trona Argus TS": {
    "type": "Transfer Station",
    "swis": "36-AA-0391",
    "addr": "Trona, San Bernardino County",
    "city": "Trona",
    "lat": 35.7624,
    "lng": -117.3769,
    "folder": "https://caiwoodgroup-my.sharepoint.com/personal/tamer_hassanein_caiwoodgroup_com/Documents/Athens/Environmental Facility Permits - Documents/Trona Argus TS",
    "permits": [
      {
        "id": "p-trona-argus-ts-01",
        "name": "Solid Waste Facility Permit",
        "agency": "San Bernardino County LEA / CalRecycle",
        "number": "36-AA-0391",
        "status": "active",
        "expires": null,
        "cycle": "",
        "area": "SWFP (SBC)",
        "doc": "https://caiwoodgroup-my.sharepoint.com/personal/tamer_hassanein_caiwoodgroup_com/Documents/Athens/Environmental Facility Permits - Documents/Trona Argus TS/SWFP (SBC)"
      }
    ],
    "leases": [],
    "checklist": []
  },
  "Newberry Springs TS": {
    "type": "Transfer Station",
    "swis": "36-AA-0371",
    "addr": "Poniente Drive, ~1/2 mi S of National Trails Hwy (Old Route 66)",
    "city": "Newberry Springs",
    "lat": 34.8281,
    "lng": -116.6864,
    "folder": "https://caiwoodgroup-my.sharepoint.com/personal/tamer_hassanein_caiwoodgroup_com/Documents/Athens/Environmental Facility Permits - Documents/Newberry Springs TS",
    "permits": [
      {
        "id": "p-newberry-springs-ts-01",
        "name": "Solid Waste Facility Permit",
        "agency": "San Bernardino County LEA / CalRecycle",
        "number": "36-AA-0371",
        "status": "active",
        "expires": null,
        "cycle": "",
        "area": "SWFP (SBC)",
        "doc": "https://caiwoodgroup-my.sharepoint.com/personal/tamer_hassanein_caiwoodgroup_com/Documents/Athens/Environmental Facility Permits - Documents/Newberry Springs TS/SWFP (SBC)"
      },
      {
        "id": "p-newberry-springs-ts-02",
        "name": "Hazardous Materials Business Plan (CUPA)",
        "agency": "San Bernardino County Fire / CUPA",
        "number": "",
        "status": "verify",
        "expires": null,
        "cycle": "",
        "area": "CUPA",
        "doc": "https://caiwoodgroup-my.sharepoint.com/personal/tamer_hassanein_caiwoodgroup_com/Documents/Athens/Environmental Facility Permits - Documents/Newberry Springs TS/CUPA"
      }
    ],
    "leases": [],
    "checklist": []
  },
  "Baker TS": {
    "type": "Transfer Station",
    "swis": "",
    "addr": "Baker, San Bernardino County",
    "city": "Baker",
    "lat": 35.2653,
    "lng": -116.0764,
    "folder": "https://caiwoodgroup-my.sharepoint.com/personal/tamer_hassanein_caiwoodgroup_com/Documents/Athens/Environmental Facility Permits - Documents/Baker TS",
    "permits": [
      {
        "id": "p-baker-ts-01",
        "name": "Solid Waste Facility Permit",
        "agency": "San Bernardino County DPH (LEA)",
        "number": "",
        "status": "verify",
        "expires": "2026-07-31",
        "cycle": "annual",
        "area": "County SB Public Health",
        "doc": "https://caiwoodgroup-my.sharepoint.com/personal/tamer_hassanein_caiwoodgroup_com/Documents/Athens/Environmental Facility Permits - Documents/Baker TS/County SB Public Health"
      }
    ],
    "leases": [],
    "checklist": []
  },
  "Camp Rock TS": {
    "type": "Transfer Station",
    "swis": "",
    "addr": "27805 Squaw Bush Road (closed Lucerne Valley LF, ~8 mi NE of Lucerne Valley)",
    "city": "Lucerne Valley",
    "lat": 34.48,
    "lng": -116.88,
    "folder": "https://caiwoodgroup-my.sharepoint.com/personal/tamer_hassanein_caiwoodgroup_com/Documents/Athens/Environmental Facility Permits - Documents/Camp Rock TS",
    "permits": [
      {
        "id": "p-camp-rock-ts-01",
        "name": "Solid Waste Facility Permit",
        "agency": "San Bernardino County LEA / CalRecycle",
        "number": "",
        "status": "verify",
        "expires": null,
        "cycle": "",
        "area": "SWFP (SBC)",
        "doc": "https://caiwoodgroup-my.sharepoint.com/personal/tamer_hassanein_caiwoodgroup_com/Documents/Athens/Environmental Facility Permits - Documents/Camp Rock TS/SWFP (SBC)"
      },
      {
        "id": "p-camp-rock-ts-02",
        "name": "County Public Health Permit to Operate",
        "agency": "San Bernardino County DPH (LEA)",
        "number": "",
        "status": "verify",
        "expires": "2026-07-31",
        "cycle": "annual",
        "area": "County SB Public Health",
        "doc": "https://caiwoodgroup-my.sharepoint.com/personal/tamer_hassanein_caiwoodgroup_com/Documents/Athens/Environmental Facility Permits - Documents/Camp Rock TS/County SB Public Health"
      }
    ],
    "leases": [],
    "checklist": []
  },
  "29 Palms TS": {
    "type": "Transfer Station",
    "swis": "36-AA-0390",
    "addr": "7501 Pinto Mountain Rd",
    "city": "Twentynine Palms",
    "lat": 34.1478,
    "lng": -116.03,
    "folder": "https://caiwoodgroup-my.sharepoint.com/personal/tamer_hassanein_caiwoodgroup_com/Documents/Athens/Environmental Facility Permits - Documents/29 Palms TS",
    "permits": [
      {
        "id": "p-29-palms-ts-01",
        "name": "Solid Waste Facility Permit",
        "agency": "CalRecycle / San Bernardino County DEHS (LEA)",
        "number": "36-AA-0390",
        "status": "active",
        "expires": null,
        "cycle": "",
        "area": "SWFP",
        "doc": "https://caiwoodgroup-my.sharepoint.com/personal/tamer_hassanein_caiwoodgroup_com/Documents/Athens/Environmental Facility Permits - Documents/29 Palms TS/SWFP (SBC)"
      },
      {
        "id": "p-29-palms-ts-02",
        "name": "Hazardous Materials Business Plan (CUPA)",
        "agency": "San Bernardino County CUPA / CERS",
        "number": "CERS ID 10038052",
        "status": "active",
        "expires": null,
        "cycle": "annual",
        "area": "CUPA",
        "doc": "https://caiwoodgroup-my.sharepoint.com/personal/tamer_hassanein_caiwoodgroup_com/Documents/Athens/Environmental Facility Permits - Documents/29 Palms TS/CUPA"
      },
      {
        "id": "p-29-palms-ts-03",
        "name": "SPCC Plan",
        "agency": "US EPA (Tier I Qualified Facility)",
        "number": "",
        "status": "active",
        "expires": null,
        "cycle": "5-year review",
        "area": "SPCC",
        "doc": "https://caiwoodgroup-my.sharepoint.com/personal/tamer_hassanein_caiwoodgroup_com/Documents/Athens/Environmental Facility Permits - Documents/29 Palms TS/SPCC"
      }
    ],
    "leases": [],
    "checklist": []
  },
  "Sheep Creek TS": {
    "type": "Transfer Station",
    "swis": "",
    "addr": "10130 Buckwheat Rd",
    "city": "Phelan",
    "lat": 34.4256,
    "lng": -117.5723,
    "folder": "https://caiwoodgroup-my.sharepoint.com/personal/tamer_hassanein_caiwoodgroup_com/Documents/Athens/Environmental Facility Permits - Documents/Sheep Creek TS",
    "permits": [
      {
        "id": "p-sheep-creek-ts-01",
        "name": "Solid Waste Facility Permit",
        "agency": "CalRecycle / San Bernardino County DEHS (LEA)",
        "number": "",
        "status": "verify",
        "expires": null,
        "cycle": "",
        "area": "SWFP",
        "doc": "https://caiwoodgroup-my.sharepoint.com/personal/tamer_hassanein_caiwoodgroup_com/Documents/Athens/Environmental Facility Permits - Documents/Sheep Creek TS/SWFP (SBC)"
      },
      {
        "id": "p-sheep-creek-ts-02",
        "name": "Hazardous Materials Business Plan (CUPA)",
        "agency": "San Bernardino County CUPA / CERS",
        "number": "CERS ID 10038007",
        "status": "active",
        "expires": null,
        "cycle": "annual",
        "area": "CUPA",
        "doc": "https://caiwoodgroup-my.sharepoint.com/personal/tamer_hassanein_caiwoodgroup_com/Documents/Athens/Environmental Facility Permits - Documents/Sheep Creek TS/CUPA"
      }
    ],
    "leases": [],
    "checklist": []
  },
  "Heaps Peak TS": {
    "type": "Transfer Station",
    "swis": "36-AA-0152",
    "addr": "29898 State Highway 18",
    "city": "Running Springs",
    "lat": 34.21,
    "lng": -117.108,
    "folder": "https://caiwoodgroup-my.sharepoint.com/personal/tamer_hassanein_caiwoodgroup_com/Documents/Athens/Environmental Facility Permits - Documents/Heaps Peak TS",
    "permits": [
      {
        "id": "p-heaps-peak-ts-01",
        "name": "Solid Waste Facility Permit",
        "agency": "CalRecycle / San Bernardino County DEHS (LEA)",
        "number": "36-AA-0152",
        "status": "active",
        "expires": null,
        "cycle": "",
        "area": "SWFP",
        "doc": "https://caiwoodgroup-my.sharepoint.com/personal/tamer_hassanein_caiwoodgroup_com/Documents/Athens/Environmental Facility Permits - Documents/Heaps Peak TS/SWFP (SBC)"
      },
      {
        "id": "p-heaps-peak-ts-02",
        "name": "Hazardous Materials Business Plan (CUPA)",
        "agency": "San Bernardino County CUPA / CERS",
        "number": "",
        "status": "verify",
        "expires": null,
        "cycle": "",
        "area": "CUPA",
        "doc": "https://caiwoodgroup-my.sharepoint.com/personal/tamer_hassanein_caiwoodgroup_com/Documents/Athens/Environmental Facility Permits - Documents/Heaps Peak TS/CUPA"
      },
      {
        "id": "p-heaps-peak-ts-03",
        "name": "SPCC Plan",
        "agency": "US EPA",
        "number": "",
        "status": "verify",
        "expires": null,
        "cycle": "",
        "area": "SPCC",
        "doc": "https://caiwoodgroup-my.sharepoint.com/personal/tamer_hassanein_caiwoodgroup_com/Documents/Athens/Environmental Facility Permits - Documents/Heaps Peak TS/SPCC"
      }
    ],
    "leases": [],
    "checklist": []
  },
  "PRR-Paramount Truck Yard": {
    "type": "Transfer Station",
    "swis": "19-AA-0840",
    "addr": "7201, 7202 & 7230 Petterson Lane",
    "city": "Paramount",
    "lat": 33.89,
    "lng": -118.162,
    "folder": "https://caiwoodgroup-my.sharepoint.com/personal/tamer_hassanein_caiwoodgroup_com/Documents/Athens/Environmental Facility Permits - Documents/PRR-Paramount Truck Yard",
    "siteMap": "https://caiwoodgroup-my.sharepoint.com/personal/tamer_hassanein_caiwoodgroup_com/Documents/Athens/Facilities Site Plan - Facilities/Paramount/2024 CUP Preliminary Site Plans, 4 Phases.pdf",
    "permits": [
      {
        "id": "p-prr-paramount-truck-ya-01",
        "name": "Solid Waste Facility Permit",
        "agency": "CalRecycle / LEA",
        "number": "19-AA-0840",
        "status": "active",
        "expires": null,
        "cycle": "5-year review",
        "area": "SWFP",
        "doc": "https://caiwoodgroup-my.sharepoint.com/personal/tamer_hassanein_caiwoodgroup_com/Documents/Athens/Environmental Facility Permits - Documents/PRR-Paramount Truck Yard/SWFP"
      },
      {
        "id": "p-prr-paramount-truck-ya-02",
        "name": "Industrial Stormwater (IGP)",
        "agency": "State Water Resources Control Board / RWQCB",
        "number": "",
        "status": "active",
        "expires": null,
        "cycle": "",
        "area": "Stormwater",
        "doc": "https://caiwoodgroup-my.sharepoint.com/personal/tamer_hassanein_caiwoodgroup_com/Documents/Athens/Environmental Facility Permits - Documents/PRR-Paramount Truck Yard/Stormwater"
      },
      {
        "id": "p-prr-paramount-truck-ya-03",
        "name": "Hazardous Materials Business Plan (CUPA)",
        "agency": "LA County CUPA (CERS)",
        "number": "",
        "status": "verify",
        "expires": null,
        "cycle": "annual",
        "area": "CUPA",
        "doc": "https://caiwoodgroup-my.sharepoint.com/personal/tamer_hassanein_caiwoodgroup_com/Documents/Athens/Environmental Facility Permits - Documents/PRR-Paramount Truck Yard/CUPA"
      },
      {
        "id": "p-prr-paramount-truck-ya-04",
        "name": "Conditional Use Permit",
        "agency": "City of Paramount Planning Department",
        "number": "",
        "status": "active",
        "expires": null,
        "cycle": "",
        "area": "CUP",
        "doc": "https://caiwoodgroup-my.sharepoint.com/personal/tamer_hassanein_caiwoodgroup_com/Documents/Athens/Environmental Facility Permits - Documents/PRR-Paramount Truck Yard/CUP"
      },
      {
        "id": "p-prr-paramount-truck-ya-05",
        "name": "Waste Discharge Requirements (WDR)",
        "agency": "RWQCB",
        "number": "",
        "status": "verify",
        "expires": null,
        "cycle": "",
        "area": "Wastewater",
        "doc": "https://caiwoodgroup-my.sharepoint.com/personal/tamer_hassanein_caiwoodgroup_com/Documents/Athens/Environmental Facility Permits - Documents/PRR-Paramount Truck Yard/Wastewater"
      }
    ],
    "leases": [],
    "checklist": []
  },
  "COI MRF": {
    "type": "Materials Recovery Facility",
    "swis": "19-AA-0863",
    "addr": "14048 Valley Blvd.",
    "city": "City of Industry",
    "lat": 34.019,
    "lng": -117.954,
    "folder": "https://caiwoodgroup-my.sharepoint.com/personal/tamer_hassanein_caiwoodgroup_com/Documents/Athens/Environmental Facility Permits - Documents/COI MRF",
    "siteMap": "https://caiwoodgroup-my.sharepoint.com/personal/tamer_hassanein_caiwoodgroup_com/Documents/Athens/Facilities Site Plan - Facilities/Valley-COI",
    "permits": [
      {
        "id": "p-coi-mrf-01",
        "name": "Solid Waste Facility Permit",
        "agency": "CalRecycle / LA County LEA",
        "number": "19-AA-0863",
        "status": "active",
        "expires": null,
        "cycle": "5-year review",
        "area": "SWFP",
        "doc": "https://caiwoodgroup-my.sharepoint.com/personal/tamer_hassanein_caiwoodgroup_com/Documents/Athens/Environmental Facility Permits - Documents/COI MRF/SWFP"
      },
      {
        "id": "p-coi-mrf-02",
        "name": "Hazardous Materials Business Plan (CUPA)",
        "agency": "CUPA via CERS",
        "number": "CERS ID 10285438",
        "status": "active",
        "expires": null,
        "cycle": "annual",
        "area": "CUPA",
        "doc": "https://caiwoodgroup-my.sharepoint.com/personal/tamer_hassanein_caiwoodgroup_com/Documents/Athens/Environmental Facility Permits - Documents/COI MRF"
      },
      {
        "id": "p-coi-mrf-03",
        "name": "Industrial Stormwater (IGP)",
        "agency": "State Water Board / LA RWQCB",
        "number": "",
        "status": "verify",
        "expires": null,
        "cycle": "annual",
        "area": "Stormwater",
        "doc": "https://caiwoodgroup-my.sharepoint.com/personal/tamer_hassanein_caiwoodgroup_com/Documents/Athens/Environmental Facility Permits - Documents/COI MRF/Stormwater"
      },
      {
        "id": "p-coi-mrf-04",
        "name": "Waste Discharge Requirements (WDR)",
        "agency": "LA RWQCB / LA County DPW",
        "number": "",
        "status": "verify",
        "expires": null,
        "cycle": "",
        "area": "Wastewater",
        "doc": "https://caiwoodgroup-my.sharepoint.com/personal/tamer_hassanein_caiwoodgroup_com/Documents/Athens/Environmental Facility Permits - Documents/COI MRF/Wastewater (clarifiers)"
      },
      {
        "id": "p-coi-mrf-05",
        "name": "SPCC Plan",
        "agency": "US EPA (self-implementing)",
        "number": "",
        "status": "verify",
        "expires": null,
        "cycle": "5-year review",
        "area": "SPCC",
        "doc": "https://caiwoodgroup-my.sharepoint.com/personal/tamer_hassanein_caiwoodgroup_com/Documents/Athens/Environmental Facility Permits - Documents/COI MRF/SPCC oil Spill"
      }
    ],
    "leases": [],
    "checklist": []
  },
  "Crown MRF": {
    "type": "Materials Recovery Facility",
    "swis": "19-AR-0303",
    "addr": "9189 De Garmo Avenue",
    "city": "Sun Valley",
    "lat": 34.2304,
    "lng": -118.3884,
    "folder": "https://caiwoodgroup-my.sharepoint.com/personal/tamer_hassanein_caiwoodgroup_com/Documents/Athens/Environmental Facility Permits - Documents/Crown MRF",
    "siteMap": "https://caiwoodgroup-my.sharepoint.com/personal/tamer_hassanein_caiwoodgroup_com/Documents/Athens/Facilities Site Plan - Facilities/Crown/2021 Site Plans/A-101 SITE PLAN_SIMPLE, ver.12-03-21.pdf",
    "permits": [
      {
        "id": "p-crown-mrf-01",
        "name": "Solid Waste Facility Permit",
        "agency": "CalRecycle / LA County LEA",
        "number": "19-AR-0303",
        "status": "active",
        "expires": null,
        "cycle": "5-year review (Nov 2021; amended Nov 2023)",
        "area": "SWFP",
        "doc": "https://caiwoodgroup-my.sharepoint.com/personal/tamer_hassanein_caiwoodgroup_com/Documents/Athens/Environmental Facility Permits - Documents/Crown MRF/SWFP"
      },
      {
        "id": "p-crown-mrf-02",
        "name": "Industrial Stormwater (IGP)",
        "agency": "State Water Board / LA RWQCB",
        "number": "",
        "status": "verify",
        "expires": null,
        "cycle": "annual",
        "area": "Stormwater",
        "doc": "https://caiwoodgroup-my.sharepoint.com/personal/tamer_hassanein_caiwoodgroup_com/Documents/Athens/Environmental Facility Permits - Documents/Crown MRF/Stormwater"
      },
      {
        "id": "p-crown-mrf-03",
        "name": "Hazardous Materials Business Plan (CUPA)",
        "agency": "CUPA",
        "number": "",
        "status": "verify",
        "expires": null,
        "cycle": "annual",
        "area": "CUPA",
        "doc": "https://caiwoodgroup-my.sharepoint.com/personal/tamer_hassanein_caiwoodgroup_com/Documents/Athens/Environmental Facility Permits - Documents/Crown MRF/CUPA"
      },
      {
        "id": "p-crown-mrf-04",
        "name": "SPCC Plan",
        "agency": "US EPA (self-implementing)",
        "number": "",
        "status": "verify",
        "expires": null,
        "cycle": "5-year review",
        "area": "SPCC",
        "doc": "https://caiwoodgroup-my.sharepoint.com/personal/tamer_hassanein_caiwoodgroup_com/Documents/Athens/Environmental Facility Permits - Documents/Crown MRF"
      },
      {
        "id": "p-crown-mrf-05",
        "name": "Waste Discharge Requirements (WDR)",
        "agency": "LA RWQCB / LA County DPW",
        "number": "",
        "status": "verify",
        "expires": null,
        "cycle": "",
        "area": "Wastewater",
        "doc": "https://caiwoodgroup-my.sharepoint.com/personal/tamer_hassanein_caiwoodgroup_com/Documents/Athens/Environmental Facility Permits - Documents/Crown MRF/Wastewater (clarifier)"
      }
    ],
    "leases": [],
    "checklist": []
  },
  "PHMRF": {
    "type": "Materials Recovery Facility",
    "swis": "",
    "addr": "13130 Crossroads Pkwy S",
    "city": "City of Industry",
    "lat": 34.006,
    "lng": -117.967,
    "folder": "https://caiwoodgroup-my.sharepoint.com/personal/tamer_hassanein_caiwoodgroup_com/Documents/Athens/Environmental Facility Permits - Documents/PHMRF",
    "permits": [
      {
        "id": "p-phmrf-01",
        "name": "EPA ID (Hazardous Waste Handler)",
        "agency": "US EPA / CA DTSC",
        "number": "CAL000473206",
        "status": "active",
        "expires": null,
        "cycle": "",
        "area": "EPA ID",
        "doc": "https://caiwoodgroup-my.sharepoint.com/personal/tamer_hassanein_caiwoodgroup_com/Documents/Athens/Environmental Facility Permits - Documents/PHMRF/EPA ID"
      },
      {
        "id": "p-phmrf-02",
        "name": "SPCC Plan",
        "agency": "US EPA (self-implementing)",
        "number": "",
        "status": "verify",
        "expires": null,
        "cycle": "5-year review",
        "area": "SPCC",
        "doc": "https://caiwoodgroup-my.sharepoint.com/personal/tamer_hassanein_caiwoodgroup_com/Documents/Athens/Environmental Facility Permits - Documents/PHMRF/SPCC oil Spill"
      }
    ],
    "leases": [],
    "checklist": []
  },
  "Irwindale MRF": {
    "type": "Materials Recovery Facility",
    "swis": "19-AA-1135",
    "addr": "2200 Arrow Highway",
    "city": "Irwindale",
    "lat": 34.1186,
    "lng": -117.954,
    "folder": "https://caiwoodgroup-my.sharepoint.com/personal/tamer_hassanein_caiwoodgroup_com/Documents/Athens/Environmental Facility Permits - Documents/Irwindale MRF",
    "siteMap": "https://caiwoodgroup-my.sharepoint.com/personal/tamer_hassanein_caiwoodgroup_com/Documents/Athens/Facilities Site Plan - Facilities/IrwindaleMRF/A1.1 Site Plan, approved 1-30-2024.pdf",
    "permits": [
      {
        "id": "p-irwindale-mrf-01",
        "name": "Solid Waste Facility Permit",
        "agency": "LA County DPH Solid Waste Mgmt (LEA) / CalRecycle",
        "number": "19-AA-1135",
        "status": "active",
        "expires": "2026-08-27",
        "cycle": "Permit review due 8/27/2026",
        "area": "SWFP",
        "doc": "https://caiwoodgroup-my.sharepoint.com/personal/tamer_hassanein_caiwoodgroup_com/Documents/Athens/Environmental Facility Permits - Documents/Irwindale MRF/SWFP"
      },
      {
        "id": "p-irwindale-mrf-02",
        "name": "Hazardous Materials Business Plan (CUPA)",
        "agency": "CUPA",
        "number": "",
        "status": "verify",
        "expires": null,
        "cycle": "",
        "area": "CUPA",
        "doc": "https://caiwoodgroup-my.sharepoint.com/personal/tamer_hassanein_caiwoodgroup_com/Documents/Athens/Environmental Facility Permits - Documents/Irwindale MRF/CUPA"
      },
      {
        "id": "p-irwindale-mrf-03",
        "name": "Industrial Stormwater (IGP)",
        "agency": "LA RWQCB / State Water Board",
        "number": "",
        "status": "verify",
        "expires": null,
        "cycle": "",
        "area": "Stormwater",
        "doc": "https://caiwoodgroup-my.sharepoint.com/personal/tamer_hassanein_caiwoodgroup_com/Documents/Athens/Environmental Facility Permits - Documents/Irwindale MRF/Stormwater"
      },
      {
        "id": "p-irwindale-mrf-04",
        "name": "Waste Discharge Requirements (WDR)",
        "agency": "LA RWQCB",
        "number": "",
        "status": "verify",
        "expires": null,
        "cycle": "",
        "area": "Wastewater",
        "doc": "https://caiwoodgroup-my.sharepoint.com/personal/tamer_hassanein_caiwoodgroup_com/Documents/Athens/Environmental Facility Permits - Documents/Irwindale MRF/Wastewater (clarifier)"
      },
      {
        "id": "p-irwindale-mrf-05",
        "name": "SPCC Plan",
        "agency": "US EPA",
        "number": "",
        "status": "verify",
        "expires": null,
        "cycle": "",
        "area": "SPCC",
        "doc": "https://caiwoodgroup-my.sharepoint.com/personal/tamer_hassanein_caiwoodgroup_com/Documents/Athens/Environmental Facility Permits - Documents/Irwindale MRF/SPCC Oil Spill"
      },
      {
        "id": "p-irwindale-mrf-06",
        "name": "Air Quality Permit to Operate",
        "agency": "South Coast AQMD",
        "number": "",
        "status": "verify",
        "expires": null,
        "cycle": "",
        "area": "Air Permits",
        "doc": "https://caiwoodgroup-my.sharepoint.com/personal/tamer_hassanein_caiwoodgroup_com/Documents/Athens/Environmental Facility Permits - Documents/Irwindale MRF/Air Permits"
      }
    ],
    "leases": [],
    "checklist": []
  },
  "DART (LACSD)": {
    "type": "Materials Recovery Facility",
    "swis": "19-AA-0801",
    "addr": "9770 Washburn Road",
    "city": "Downey",
    "lat": 33.918,
    "lng": -118.118,
    "folder": "https://caiwoodgroup-my.sharepoint.com/personal/tamer_hassanein_caiwoodgroup_com/Documents/Athens/Environmental Facility Permits - Documents/DART (LACSD)",
    "permits": [
      {
        "id": "p-dart-lacsd-01",
        "name": "Solid Waste Facility Permit",
        "agency": "LA County Dept of Public Health (LEA)",
        "number": "19-AA-0801",
        "status": "active",
        "expires": "2027-01-19",
        "cycle": "5-year review",
        "area": "SWFP",
        "doc": "https://caiwoodgroup-my.sharepoint.com/personal/tamer_hassanein_caiwoodgroup_com/Documents/Athens/Environmental Facility Permits - Documents/DART (LACSD)/SWFP"
      },
      {
        "id": "p-dart-lacsd-02",
        "name": "Hazardous Materials Business Plan (CUPA)",
        "agency": "CUPA",
        "number": "",
        "status": "verify",
        "expires": null,
        "cycle": "annual",
        "area": "CUPA",
        "doc": "https://caiwoodgroup-my.sharepoint.com/personal/tamer_hassanein_caiwoodgroup_com/Documents/Athens/Environmental Facility Permits - Documents/DART (LACSD)/CUPA"
      },
      {
        "id": "p-dart-lacsd-03",
        "name": "Industrial Stormwater (IGP)",
        "agency": "State Water Resources Control Board (RWQCB Region 4)",
        "number": "WDID 4 19I029847",
        "status": "active",
        "expires": null,
        "cycle": "annual",
        "area": "Stormwater",
        "doc": "https://caiwoodgroup-my.sharepoint.com/personal/tamer_hassanein_caiwoodgroup_com/Documents/Athens/Environmental Facility Permits - Documents/DART (LACSD)/Stormwater (SWPPP)"
      },
      {
        "id": "p-dart-lacsd-04",
        "name": "Waste Discharge Requirements (WDR)",
        "agency": "LA County Sanitation Districts",
        "number": "22835",
        "status": "active",
        "expires": "2031-03-16",
        "cycle": "5-year",
        "area": "Wastewater",
        "doc": "https://caiwoodgroup-my.sharepoint.com/personal/tamer_hassanein_caiwoodgroup_com/Documents/Athens/Environmental Facility Permits - Documents/DART (LACSD)/Wastewater"
      },
      {
        "id": "p-dart-lacsd-05",
        "name": "SPCC Plan",
        "agency": "Self-certified (Tier 1)",
        "number": "",
        "status": "verify",
        "expires": null,
        "cycle": "5-year review",
        "area": "SPCC",
        "doc": "https://caiwoodgroup-my.sharepoint.com/personal/tamer_hassanein_caiwoodgroup_com/Documents/Athens/Environmental Facility Permits - Documents/DART (LACSD)/Spcc Plan"
      }
    ],
    "leases": [],
    "checklist": []
  },
  "Victorville LF": {
    "type": "Landfill",
    "swis": "36-AA-0045",
    "addr": "18600 Stoddard Wells Road",
    "city": "Victorville",
    "lat": 34.583,
    "lng": -117.296,
    "folder": "https://caiwoodgroup-my.sharepoint.com/personal/tamer_hassanein_caiwoodgroup_com/Documents/Athens/Environmental Facility Permits - Documents/Victorville LF",
    "permits": [
      {
        "id": "p-victorville-lf-01",
        "name": "Solid Waste Facility Permit",
        "agency": "CalRecycle / San Bernardino County (LEA)",
        "number": "",
        "status": "verify",
        "expires": null,
        "cycle": "5-year review",
        "area": "SWFP (SBC)",
        "doc": "https://caiwoodgroup-my.sharepoint.com/personal/tamer_hassanein_caiwoodgroup_com/Documents/Athens/Environmental Facility Permits - Documents/Victorville LF/SWFP (SBC)"
      },
      {
        "id": "p-victorville-lf-02",
        "name": "Hazardous Materials Business Plan (CUPA)",
        "agency": "San Bernardino County CUPA",
        "number": "",
        "status": "verify",
        "expires": null,
        "cycle": "annual",
        "area": "CUPA",
        "doc": "https://caiwoodgroup-my.sharepoint.com/personal/tamer_hassanein_caiwoodgroup_com/Documents/Athens/Environmental Facility Permits - Documents/Victorville LF/CUPA"
      },
      {
        "id": "p-victorville-lf-03",
        "name": "Waste Discharge Requirements (WDR)",
        "agency": "RWQCB - Lahontan Region",
        "number": "R6V-2004-0027",
        "status": "active",
        "expires": null,
        "cycle": "",
        "area": "WDR (SBC)",
        "doc": "https://caiwoodgroup-my.sharepoint.com/personal/tamer_hassanein_caiwoodgroup_com/Documents/Athens/Environmental Facility Permits - Documents/Victorville LF/WDR (SBC)"
      },
      {
        "id": "p-victorville-lf-04",
        "name": "Title V Federal Operating Permit (Air)",
        "agency": "Mojave Desert AQMD (MDAQMD)",
        "number": "102102443",
        "status": "active",
        "expires": null,
        "cycle": "5-year",
        "area": "Air Permits",
        "doc": "https://caiwoodgroup-my.sharepoint.com/personal/tamer_hassanein_caiwoodgroup_com/Documents/Athens/Environmental Facility Permits - Documents/Victorville LF/Air Permits"
      }
    ],
    "leases": [],
    "checklist": []
  },
  "Mid Valley LF": {
    "type": "Landfill",
    "swis": "36-AA-0055",
    "addr": "2390 North Alder Avenue",
    "city": "Rialto",
    "lat": 34.135,
    "lng": -117.43,
    "folder": "https://caiwoodgroup-my.sharepoint.com/personal/tamer_hassanein_caiwoodgroup_com/Documents/Athens/Environmental Facility Permits - Documents/Mid Valley LF",
    "permits": [
      {
        "id": "p-mid-valley-lf-01",
        "name": "Solid Waste Facility Permit",
        "agency": "CalRecycle / San Bernardino County (LEA)",
        "number": "36-AA-0055",
        "status": "verify",
        "expires": null,
        "cycle": "5-year review",
        "area": "SWFP",
        "doc": "https://caiwoodgroup-my.sharepoint.com/personal/tamer_hassanein_caiwoodgroup_com/Documents/Athens/Environmental Facility Permits - Documents/Mid Valley LF/SWFP (SBC)"
      },
      {
        "id": "p-mid-valley-lf-02",
        "name": "Hazardous Materials Business Plan (CUPA)",
        "agency": "San Bernardino County CUPA (Fire Protection District)",
        "number": "CERS ID 10037911",
        "status": "active",
        "expires": null,
        "cycle": "annual",
        "area": "CUPA",
        "doc": "https://caiwoodgroup-my.sharepoint.com/personal/tamer_hassanein_caiwoodgroup_com/Documents/Athens/Environmental Facility Permits - Documents/Mid Valley LF/CUPA"
      },
      {
        "id": "p-mid-valley-lf-03",
        "name": "Waste Discharge Requirements (WDR)",
        "agency": "California RWQCB, Santa Ana Region (R8)",
        "number": "Order 98-095 (amd R8-2006-0040, R8-2016-0052)",
        "status": "active",
        "expires": null,
        "cycle": "",
        "area": "WDR",
        "doc": "https://caiwoodgroup-my.sharepoint.com/personal/tamer_hassanein_caiwoodgroup_com/Documents/Athens/Environmental Facility Permits - Documents/Mid Valley LF/WDR (SBC)"
      },
      {
        "id": "p-mid-valley-lf-04",
        "name": "SPCC Plan",
        "agency": "US EPA (self-implementing)",
        "number": "",
        "status": "verify",
        "expires": null,
        "cycle": "5-year review",
        "area": "SPCC",
        "doc": "https://caiwoodgroup-my.sharepoint.com/personal/tamer_hassanein_caiwoodgroup_com/Documents/Athens/Environmental Facility Permits - Documents/Mid Valley LF/SPCC"
      }
    ],
    "leases": [],
    "checklist": []
  },
  "Barstow LF": {
    "type": "Landfill",
    "swis": "36-AA-0046",
    "addr": "32553 Barstow Rd",
    "city": "Barstow",
    "lat": 34.8,
    "lng": -117.02,
    "folder": "https://caiwoodgroup-my.sharepoint.com/personal/tamer_hassanein_caiwoodgroup_com/Documents/Athens/Environmental Facility Permits - Documents/Barstow LF",
    "permits": [
      {
        "id": "p-barstow-lf-01",
        "name": "Solid Waste Facility Permit",
        "agency": "CalRecycle / San Bernardino County DEHS (LEA)",
        "number": "36-AA-0046",
        "status": "active",
        "expires": "2029-10-25",
        "cycle": "Permit review due",
        "area": "SWFP",
        "doc": "https://caiwoodgroup-my.sharepoint.com/personal/tamer_hassanein_caiwoodgroup_com/Documents/Athens/Environmental Facility Permits - Documents/Barstow LF/SWFP (SBC)"
      },
      {
        "id": "p-barstow-lf-02",
        "name": "Waste Discharge Requirements (WDR)",
        "agency": "Lahontan RWQCB (Region 6)",
        "number": "Order R6V-2022-0009 / WDID 6B360304005",
        "status": "active",
        "expires": null,
        "cycle": "",
        "area": "WDR (SBC)",
        "doc": "https://caiwoodgroup-my.sharepoint.com/personal/tamer_hassanein_caiwoodgroup_com/Documents/Athens/Environmental Facility Permits - Documents/Barstow LF/WDR (SBC)"
      },
      {
        "id": "p-barstow-lf-03",
        "name": "Hazardous Materials Business Plan (CUPA)",
        "agency": "San Bernardino County CUPA / CERS",
        "number": "",
        "status": "verify",
        "expires": null,
        "cycle": "",
        "area": "CUPA",
        "doc": "https://caiwoodgroup-my.sharepoint.com/personal/tamer_hassanein_caiwoodgroup_com/Documents/Athens/Environmental Facility Permits - Documents/Barstow LF/CUPA"
      }
    ],
    "leases": [],
    "checklist": []
  },
  "Landers LF": {
    "type": "Landfill",
    "swis": "36-AA-0057",
    "addr": "59200 Winters Road",
    "city": "Landers",
    "lat": 34.318,
    "lng": -116.434,
    "folder": "https://caiwoodgroup-my.sharepoint.com/personal/tamer_hassanein_caiwoodgroup_com/Documents/Athens/Environmental Facility Permits - Documents/Landers LF",
    "permits": [
      {
        "id": "p-landers-lf-01",
        "name": "Solid Waste Facility Permit",
        "agency": "CalRecycle / San Bernardino County DEHS (LEA)",
        "number": "36-AA-0057",
        "status": "active",
        "expires": "2027-01-27",
        "cycle": "Permit review due",
        "area": "SWFP",
        "doc": "https://caiwoodgroup-my.sharepoint.com/personal/tamer_hassanein_caiwoodgroup_com/Documents/Athens/Environmental Facility Permits - Documents/Landers LF/SWFP (SBC)"
      },
      {
        "id": "p-landers-lf-02",
        "name": "Waste Discharge Requirements (WDR)",
        "agency": "Lahontan RWQCB (Region 7)",
        "number": "Order R7-2009-0063 / WDID 736I005246",
        "status": "active",
        "expires": null,
        "cycle": "",
        "area": "WDR (SBC)",
        "doc": "https://caiwoodgroup-my.sharepoint.com/personal/tamer_hassanein_caiwoodgroup_com/Documents/Athens/Environmental Facility Permits - Documents/Landers LF/WDR (SBC)"
      }
    ],
    "leases": [],
    "checklist": []
  },
  "San Timoteo LF": {
    "type": "Landfill",
    "swis": "36-AA-0087",
    "addr": "San Timoteo Canyon Rd, Redlands",
    "city": "Redlands",
    "lat": 34.015,
    "lng": -117.15,
    "folder": "https://caiwoodgroup-my.sharepoint.com/personal/tamer_hassanein_caiwoodgroup_com/Documents/Athens/Environmental Facility Permits - Documents/San Timoteo LF",
    "permits": [
      {
        "id": "p-san-timoteo-lf-01",
        "name": "Solid Waste Facility Permit",
        "agency": "CalRecycle / San Bernardino County (LEA)",
        "number": "36-AA-0087",
        "status": "active",
        "expires": "2027-10-21",
        "cycle": "5-year",
        "area": "SWFP (SBC)",
        "doc": "https://caiwoodgroup-my.sharepoint.com/personal/tamer_hassanein_caiwoodgroup_com/Documents/Athens/Environmental Facility Permits - Documents/San Timoteo LF/SWFP (SBC)"
      },
      {
        "id": "p-san-timoteo-lf-02",
        "name": "Waste Discharge Requirements (WDR)",
        "agency": "RWQCB (Santa Ana Region)",
        "number": "78-151",
        "status": "active",
        "expires": null,
        "cycle": "",
        "area": "JTD",
        "doc": "https://caiwoodgroup-my.sharepoint.com/personal/tamer_hassanein_caiwoodgroup_com/Documents/Athens/Environmental Facility Permits - Documents/San Timoteo LF/SWFP (SBC)"
      },
      {
        "id": "p-san-timoteo-lf-03",
        "name": "Hazardous Materials Business Plan (CUPA)",
        "agency": "San Bernardino County CUPA",
        "number": "",
        "status": "active",
        "expires": "2026-06-30",
        "cycle": "annual",
        "area": "CUPA",
        "doc": "https://caiwoodgroup-my.sharepoint.com/personal/tamer_hassanein_caiwoodgroup_com/Documents/Athens/Environmental Facility Permits - Documents/San Timoteo LF/CUPA"
      },
      {
        "id": "p-san-timoteo-lf-04",
        "name": "County Public Health Permit to Operate",
        "agency": "San Bernardino County Public Health",
        "number": "",
        "status": "active",
        "expires": "2026-07-31",
        "cycle": "annual",
        "area": "County SB Public Health",
        "doc": "https://caiwoodgroup-my.sharepoint.com/personal/tamer_hassanein_caiwoodgroup_com/Documents/Athens/Environmental Facility Permits - Documents/San Timoteo LF/County SB Public Health"
      }
    ],
    "leases": [],
    "checklist": []
  },
  "American Organics (VVRCF)": {
    "type": "Compost / Organics",
    "swis": "36-AA-0403",
    "addr": "20055 Shay Road",
    "city": "Victorville",
    "lat": 34.612,
    "lng": -117.379,
    "folder": "https://caiwoodgroup-my.sharepoint.com/personal/tamer_hassanein_caiwoodgroup_com/Documents/Athens/Environmental Facility Permits - Documents/American Organics (VVRCF)",
    "siteMap": "https://caiwoodgroup-my.sharepoint.com/personal/tamer_hassanein_caiwoodgroup_com/Documents/Athens/Facilities Site Plan - Facilities/AO-VVRCF",
    "permits": [
      {
        "id": "p-american-organics-vvrc-01",
        "name": "Solid Waste Facility Permit",
        "agency": "San Bernardino County (LEA) / CalRecycle",
        "number": "36-AA-0403",
        "status": "active",
        "expires": null,
        "cycle": "RCSI revised Jan 2023",
        "area": "SWFP",
        "doc": "https://caiwoodgroup-my.sharepoint.com/personal/tamer_hassanein_caiwoodgroup_com/Documents/Athens/Environmental Facility Permits - Documents/American Organics (VVRCF)/SWFP"
      },
      {
        "id": "p-american-organics-vvrc-02",
        "name": "Hazardous Materials Business Plan (CUPA)",
        "agency": "San Bernardino County CUPA",
        "number": "",
        "status": "verify",
        "expires": null,
        "cycle": "",
        "area": "CUPA",
        "doc": "https://caiwoodgroup-my.sharepoint.com/personal/tamer_hassanein_caiwoodgroup_com/Documents/Athens/Environmental Facility Permits - Documents/American Organics (VVRCF)/CUPA haz mat"
      },
      {
        "id": "p-american-organics-vvrc-03",
        "name": "Industrial Stormwater (IGP)",
        "agency": "Lahontan / Colorado River Basin RWQCB / State Water Board",
        "number": "",
        "status": "verify",
        "expires": null,
        "cycle": "",
        "area": "Stormwater",
        "doc": "https://caiwoodgroup-my.sharepoint.com/personal/tamer_hassanein_caiwoodgroup_com/Documents/Athens/Environmental Facility Permits - Documents/American Organics (VVRCF)/Stormwater"
      },
      {
        "id": "p-american-organics-vvrc-04",
        "name": "Waste Discharge Requirements (WDR)",
        "agency": "RWQCB",
        "number": "",
        "status": "verify",
        "expires": null,
        "cycle": "",
        "area": "WDR",
        "doc": "https://caiwoodgroup-my.sharepoint.com/personal/tamer_hassanein_caiwoodgroup_com/Documents/Athens/Environmental Facility Permits - Documents/American Organics (VVRCF)/WDR"
      },
      {
        "id": "p-american-organics-vvrc-05",
        "name": "SPCC Plan",
        "agency": "US EPA",
        "number": "",
        "status": "verify",
        "expires": null,
        "cycle": "",
        "area": "SPCC",
        "doc": "https://caiwoodgroup-my.sharepoint.com/personal/tamer_hassanein_caiwoodgroup_com/Documents/Athens/Environmental Facility Permits - Documents/American Organics (VVRCF)/SPCC Oil Spill"
      },
      {
        "id": "p-american-organics-vvrc-06",
        "name": "Air Quality Permit to Operate",
        "agency": "Mojave Desert AQMD (MDAQMD)",
        "number": "",
        "status": "verify",
        "expires": null,
        "cycle": "",
        "area": "Air Permits",
        "doc": "https://caiwoodgroup-my.sharepoint.com/personal/tamer_hassanein_caiwoodgroup_com/Documents/Athens/Environmental Facility Permits - Documents/American Organics (VVRCF)/Air Permits - MDAQMD"
      }
    ],
    "leases": [],
    "checklist": []
  },
  "Irwindale IOC": {
    "type": "Office / Other",
    "swis": "",
    "addr": "4777 Irwindale Ave",
    "city": "Irwindale",
    "lat": 34.107,
    "lng": -117.954,
    "anchor": true,
    "folder": "https://caiwoodgroup-my.sharepoint.com/personal/tamer_hassanein_caiwoodgroup_com/Documents/Athens/Environmental Facility Permits - Documents/Irwindale IOC",
    "permits": [
      {
        "id": "p-irwindale-ioc-01",
        "name": "Hazardous Materials Business Plan (CUPA)",
        "agency": "LA County (CUPA) / CERS",
        "number": "CERS ID 10148839 / FA0044010",
        "status": "active",
        "expires": null,
        "cycle": "annual",
        "area": "CUPA",
        "doc": "https://caiwoodgroup-my.sharepoint.com/personal/tamer_hassanein_caiwoodgroup_com/Documents/Athens/Environmental Facility Permits - Documents/Irwindale IOC/CUPA"
      },
      {
        "id": "p-irwindale-ioc-02",
        "name": "Air Permit (Boiler)",
        "agency": "South Coast AQMD",
        "number": "Facility ID 208296",
        "status": "verify",
        "expires": null,
        "cycle": "",
        "area": "Air Permits",
        "doc": "https://caiwoodgroup-my.sharepoint.com/personal/tamer_hassanein_caiwoodgroup_com/Documents/Athens/Environmental Facility Permits - Documents/Irwindale IOC/Air Permits"
      }
    ],
    "leases": [],
    "checklist": []
  },
  "Salt Lake": {
    "type": "Hauling Yard",
    "swis": "",
    "addr": "15045 Salt Lake Avenue",
    "city": "City of Industry",
    "lat": 34.019,
    "lng": -117.945,
    "folder": "https://caiwoodgroup-my.sharepoint.com/personal/tamer_hassanein_caiwoodgroup_com/Documents/Athens/Environmental Facility Permits - Documents/Salt Lake",
    "siteMap": "https://caiwoodgroup-my.sharepoint.com/personal/tamer_hassanein_caiwoodgroup_com/Documents/Athens/Facilities Site Plan - Facilities/Salt Lake/Site Plan approved by County 12-18-24, CUP Exhibit A.pdf",
    "permits": [
      {
        "id": "p-salt-lake-01",
        "name": "Industrial Stormwater (IGP)",
        "agency": "State Water Resources Control Board / RWQCB",
        "number": "",
        "status": "active",
        "expires": null,
        "cycle": "",
        "area": "Stormwater",
        "doc": "https://caiwoodgroup-my.sharepoint.com/personal/tamer_hassanein_caiwoodgroup_com/Documents/Athens/Environmental Facility Permits - Documents/Salt Lake/Stormwater"
      },
      {
        "id": "p-salt-lake-02",
        "name": "Hazardous Materials Business Plan (CUPA)",
        "agency": "LA County CUPA (CERS)",
        "number": "CERS ID 10273117",
        "status": "active",
        "expires": null,
        "cycle": "annual",
        "area": "CUPA",
        "doc": "https://caiwoodgroup-my.sharepoint.com/personal/tamer_hassanein_caiwoodgroup_com/Documents/Athens/Environmental Facility Permits - Documents/Salt Lake/CUPA haz mat"
      },
      {
        "id": "p-salt-lake-03",
        "name": "Waste Discharge Requirements (WDR)",
        "agency": "RWQCB",
        "number": "",
        "status": "verify",
        "expires": null,
        "cycle": "",
        "area": "Wastewater (clarifier)",
        "doc": "https://caiwoodgroup-my.sharepoint.com/personal/tamer_hassanein_caiwoodgroup_com/Documents/Athens/Environmental Facility Permits - Documents/Salt Lake/Wastewater (clarifier)"
      }
    ],
    "leases": [],
    "checklist": []
  },
  "Van Norman": {
    "type": "Operations Yard",
    "swis": "",
    "addr": "127 Van Norman Road",
    "city": "Montebello",
    "lat": 34.01,
    "lng": -118.113,
    "folder": "https://caiwoodgroup-my.sharepoint.com/personal/tamer_hassanein_caiwoodgroup_com/Documents/Athens/Environmental Facility Permits - Documents/Van Norman",
    "siteMap": "https://caiwoodgroup-my.sharepoint.com/personal/tamer_hassanein_caiwoodgroup_com/Documents/Athens/Facilities Site Plan - Facilities/Van Norman/Site Map, Stormwater 2024.pdf",
    "permits": [
      {
        "id": "p-van-norman-01",
        "name": "Industrial Stormwater (IGP)",
        "agency": "State Water Resources Control Board / RWQCB",
        "number": "",
        "status": "active",
        "expires": null,
        "cycle": "",
        "area": "Stormwater",
        "doc": "https://caiwoodgroup-my.sharepoint.com/personal/tamer_hassanein_caiwoodgroup_com/Documents/Athens/Environmental Facility Permits - Documents/Van Norman/Stormwater"
      },
      {
        "id": "p-van-norman-02",
        "name": "Hazardous Materials Business Plan (CUPA)",
        "agency": "LA County CUPA (CERS)",
        "number": "CERS ID 10282906 / FA LACoFA0027441",
        "status": "active",
        "expires": null,
        "cycle": "annual",
        "area": "CUPA",
        "doc": "https://caiwoodgroup-my.sharepoint.com/personal/tamer_hassanein_caiwoodgroup_com/Documents/Athens/Environmental Facility Permits - Documents/Van Norman/CUPA haz mat"
      },
      {
        "id": "p-van-norman-03",
        "name": "Waste Discharge Requirements (WDR)",
        "agency": "RWQCB",
        "number": "",
        "status": "verify",
        "expires": null,
        "cycle": "",
        "area": "Wastewater (clarifier)",
        "doc": "https://caiwoodgroup-my.sharepoint.com/personal/tamer_hassanein_caiwoodgroup_com/Documents/Athens/Environmental Facility Permits - Documents/Van Norman/Wastewater (clarifier)"
      }
    ],
    "leases": [],
    "checklist": []
  },
  "TO-Hillcrest": {
    "type": "Hauling Yard",
    "swis": "",
    "addr": "225 W Hillcrest Drive",
    "city": "Thousand Oaks",
    "lat": 34.196,
    "lng": -118.876,
    "folder": "https://caiwoodgroup-my.sharepoint.com/personal/tamer_hassanein_caiwoodgroup_com/Documents/Athens/Environmental Facility Permits - Documents/TO-Hillcrest",
    "permits": [
      {
        "id": "p-to-hillcrest-01",
        "name": "Industrial Stormwater (IGP)",
        "agency": "State Water Resources Control Board / Ventura RWQCB",
        "number": "WDID 456I029957",
        "status": "active",
        "expires": null,
        "cycle": "",
        "area": "Stormwater",
        "doc": "https://caiwoodgroup-my.sharepoint.com/personal/tamer_hassanein_caiwoodgroup_com/Documents/Athens/Environmental Facility Permits - Documents/TO-Hillcrest/Stormwater"
      }
    ],
    "leases": [],
    "checklist": []
  },
  "TO-Conejo Center Dr": {
    "type": "Operations Yard",
    "swis": "",
    "addr": "2550 Conejo Center Drive",
    "city": "Thousand Oaks",
    "lat": 34.187,
    "lng": -118.937,
    "folder": "https://caiwoodgroup-my.sharepoint.com/personal/tamer_hassanein_caiwoodgroup_com/Documents/Athens/Environmental Facility Permits - Documents/TO-Conejo Center Dr",
    "siteMap": "https://caiwoodgroup-my.sharepoint.com/personal/tamer_hassanein_caiwoodgroup_com/Documents/Athens/Facilities Site Plan - Facilities/TO-Conejo/2021.09.10 TO Site Plan drawings.pdf",
    "permits": [
      {
        "id": "p-to-conejo-center-dr-01",
        "name": "Hazardous Materials Business Plan (CUPA)",
        "agency": "Ventura County CUPA (CERS)",
        "number": "CERS ID 10962301 / EPA ID CAL000487902",
        "status": "active",
        "expires": null,
        "cycle": "annual",
        "area": "CUPA",
        "doc": "https://caiwoodgroup-my.sharepoint.com/personal/tamer_hassanein_caiwoodgroup_com/Documents/Athens/Environmental Facility Permits - Documents/TO-Conejo Center Dr/CUPA"
      },
      {
        "id": "p-to-conejo-center-dr-02",
        "name": "SPCC Plan",
        "agency": "US EPA (self-certified)",
        "number": "",
        "status": "active",
        "expires": null,
        "cycle": "5-year review (last 9/16/2024)",
        "area": "SPCC",
        "doc": "https://caiwoodgroup-my.sharepoint.com/personal/tamer_hassanein_caiwoodgroup_com/Documents/Athens/Environmental Facility Permits - Documents/TO-Conejo Center Dr/SPCC"
      },
      {
        "id": "p-to-conejo-center-dr-03",
        "name": "Waste Discharge Requirements (WDR)",
        "agency": "RWQCB",
        "number": "",
        "status": "verify",
        "expires": null,
        "cycle": "",
        "area": "Wastewater",
        "doc": "https://caiwoodgroup-my.sharepoint.com/personal/tamer_hassanein_caiwoodgroup_com/Documents/Athens/Environmental Facility Permits - Documents/TO-Conejo Center Dr/Wastewater"
      }
    ],
    "leases": [],
    "checklist": []
  },
  "Lopez Canyon": {
    "type": "Hauling Yard",
    "swis": "",
    "addr": "12221 N Lopez Canyon Rd",
    "city": "Sylmar",
    "lat": 34.33,
    "lng": -118.379,
    "folder": "https://caiwoodgroup-my.sharepoint.com/personal/tamer_hassanein_caiwoodgroup_com/Documents/Athens/Environmental Facility Permits - Documents/Lopez Canyon",
    "permits": [
      {
        "id": "p-lopez-canyon-01",
        "name": "County of LA Waste Collector Permit (WCP)",
        "agency": "County of Los Angeles",
        "number": "",
        "status": "verify",
        "expires": null,
        "cycle": "",
        "area": "WCP",
        "doc": "https://caiwoodgroup-my.sharepoint.com/personal/tamer_hassanein_caiwoodgroup_com/Documents/Athens/Environmental Facility Permits - Documents/Lopez Canyon/County LA Waste Collector - yard only"
      },
      {
        "id": "p-lopez-canyon-02",
        "name": "EPA ID (Hazardous Waste Generator)",
        "agency": "US EPA / CA DTSC",
        "number": "CAL000468896",
        "status": "active",
        "expires": null,
        "cycle": "",
        "area": "EPA ID",
        "doc": "https://caiwoodgroup-my.sharepoint.com/personal/tamer_hassanein_caiwoodgroup_com/Documents/Athens/Environmental Facility Permits - Documents/Lopez Canyon"
      }
    ],
    "leases": [],
    "checklist": []
  },
  "LA South": {
    "type": "Operations Yard",
    "swis": "",
    "addr": "1301 W. 228th Street",
    "city": "Torrance",
    "lat": 33.823,
    "lng": -118.299,
    "folder": "https://caiwoodgroup-my.sharepoint.com/personal/tamer_hassanein_caiwoodgroup_com/Documents/Athens/Environmental Facility Permits - Documents/LA South",
    "siteMap": "https://caiwoodgroup-my.sharepoint.com/personal/tamer_hassanein_caiwoodgroup_com/Documents/Athens/Facilities Site Plan - Facilities/LASO/2025 LASO Stormwater Site Map.pdf",
    "permits": [
      {
        "id": "p-la-south-01",
        "name": "Industrial Stormwater (IGP)",
        "agency": "State Water Resources Control Board (LA RWQCB)",
        "number": "WDID 4 19I025344",
        "status": "active",
        "expires": null,
        "cycle": "",
        "area": "Stormwater",
        "doc": "https://caiwoodgroup-my.sharepoint.com/personal/tamer_hassanein_caiwoodgroup_com/Documents/Athens/Environmental Facility Permits - Documents/LA South"
      },
      {
        "id": "p-la-south-02",
        "name": "Hazardous Materials Business Plan (CUPA)",
        "agency": "CUPA",
        "number": "",
        "status": "verify",
        "expires": null,
        "cycle": "",
        "area": "CUPA",
        "doc": "https://caiwoodgroup-my.sharepoint.com/personal/tamer_hassanein_caiwoodgroup_com/Documents/Athens/Environmental Facility Permits - Documents/LA South/CUPA Haz Mat"
      },
      {
        "id": "p-la-south-03",
        "name": "SPCC Plan",
        "agency": "US EPA (self-certified)",
        "number": "",
        "status": "verify",
        "expires": null,
        "cycle": "",
        "area": "SPCC",
        "doc": "https://caiwoodgroup-my.sharepoint.com/personal/tamer_hassanein_caiwoodgroup_com/Documents/Athens/Environmental Facility Permits - Documents/LA South/SPCC Oil Spill"
      }
    ],
    "leases": [],
    "checklist": []
  },
  "LA North": {
    "type": "Operations Yard",
    "swis": "",
    "addr": "12303 Montague Street",
    "city": "Pacoima",
    "lat": 34.262,
    "lng": -118.412,
    "folder": "https://caiwoodgroup-my.sharepoint.com/personal/tamer_hassanein_caiwoodgroup_com/Documents/Athens/Environmental Facility Permits - Documents/LA North",
    "siteMap": "https://caiwoodgroup-my.sharepoint.com/personal/tamer_hassanein_caiwoodgroup_com/Documents/Athens/Facilities Site Plan - Facilities/LANO/Site.Plan.Montague.revised.09.04.15.pdf",
    "permits": [
      {
        "id": "p-la-north-01",
        "name": "Industrial Stormwater (IGP)",
        "agency": "State Water Resources Control Board (LA RWQCB)",
        "number": "WDID 4 19I025398",
        "status": "active",
        "expires": null,
        "cycle": "",
        "area": "Stormwater",
        "doc": "https://caiwoodgroup-my.sharepoint.com/personal/tamer_hassanein_caiwoodgroup_com/Documents/Athens/Environmental Facility Permits - Documents/LA North/Stormwater"
      },
      {
        "id": "p-la-north-02",
        "name": "SPCC Plan",
        "agency": "US EPA (self-certified)",
        "number": "",
        "status": "verify",
        "expires": null,
        "cycle": "",
        "area": "SPCC",
        "doc": "https://caiwoodgroup-my.sharepoint.com/personal/tamer_hassanein_caiwoodgroup_com/Documents/Athens/Environmental Facility Permits - Documents/LA North/SPCC Oil Spill"
      },
      {
        "id": "p-la-north-03",
        "name": "Waste Discharge Requirements (WDR)",
        "agency": "LA RWQCB",
        "number": "",
        "status": "verify",
        "expires": null,
        "cycle": "",
        "area": "Wastewater (clarifier)",
        "doc": "https://caiwoodgroup-my.sharepoint.com/personal/tamer_hassanein_caiwoodgroup_com/Documents/Athens/Environmental Facility Permits - Documents/LA North/Wastewater (clarifier)"
      }
    ],
    "leases": [],
    "checklist": []
  },
  "Santa Paula": {
    "type": "Hauling Yard",
    "swis": "",
    "addr": "905 Corporation Street",
    "city": "Santa Paula",
    "lat": 34.354,
    "lng": -119.072,
    "folder": "https://caiwoodgroup-my.sharepoint.com/personal/tamer_hassanein_caiwoodgroup_com/Documents/Athens/Environmental Facility Permits - Documents/Santa Paula",
    "permits": [
      {
        "id": "p-santa-paula-01",
        "name": "Industrial Stormwater (IGP)",
        "agency": "State Water Resources Control Board (LA RWQCB)",
        "number": "WDID 4 56I028659",
        "status": "active",
        "expires": null,
        "cycle": "",
        "area": "Stormwater",
        "doc": "https://caiwoodgroup-my.sharepoint.com/personal/tamer_hassanein_caiwoodgroup_com/Documents/Athens/Environmental Facility Permits - Documents/Santa Paula/Stormwater"
      }
    ],
    "leases": [],
    "checklist": []
  },
  "Riverside": {
    "type": "Hauling Yard",
    "swis": "",
    "addr": "687 Iowa Avenue",
    "city": "Riverside",
    "lat": 33.998,
    "lng": -117.339,
    "folder": "https://caiwoodgroup-my.sharepoint.com/personal/tamer_hassanein_caiwoodgroup_com/Documents/Athens/Environmental Facility Permits - Documents/Riverside",
    "siteMap": "https://caiwoodgroup-my.sharepoint.com/personal/tamer_hassanein_caiwoodgroup_com/Documents/Athens/Facilities Site Plan - Facilities/Riverside",
    "permits": [
      {
        "id": "p-riverside-01",
        "name": "Industrial Stormwater (IGP)",
        "agency": "State Water Resources Control Board (Region 8 - Santa Ana RWQCB)",
        "number": "WDID 8 33I024182",
        "status": "active",
        "expires": null,
        "cycle": "",
        "area": "Stormwater",
        "doc": "https://caiwoodgroup-my.sharepoint.com/personal/tamer_hassanein_caiwoodgroup_com/Documents/Athens/Environmental Facility Permits - Documents/Riverside/Stormwater"
      },
      {
        "id": "p-riverside-02",
        "name": "Hazardous Materials Business Plan (CUPA)",
        "agency": "CUPA",
        "number": "",
        "status": "verify",
        "expires": null,
        "cycle": "",
        "area": "CUPA",
        "doc": "https://caiwoodgroup-my.sharepoint.com/personal/tamer_hassanein_caiwoodgroup_com/Documents/Athens/Environmental Facility Permits - Documents/Riverside/CUPA haz mat"
      },
      {
        "id": "p-riverside-03",
        "name": "SPCC Plan",
        "agency": "US EPA (self-certified)",
        "number": "",
        "status": "verify",
        "expires": null,
        "cycle": "",
        "area": "SPCC",
        "doc": "https://caiwoodgroup-my.sharepoint.com/personal/tamer_hassanein_caiwoodgroup_com/Documents/Athens/Environmental Facility Permits - Documents/Riverside/SPCC Oil Spill"
      },
      {
        "id": "p-riverside-04",
        "name": "Waste Discharge Requirements (WDR)",
        "agency": "Santa Ana RWQCB",
        "number": "",
        "status": "verify",
        "expires": null,
        "cycle": "",
        "area": "Wastewater (clarifier)",
        "doc": "https://caiwoodgroup-my.sharepoint.com/personal/tamer_hassanein_caiwoodgroup_com/Documents/Athens/Environmental Facility Permits - Documents/Riverside/Wastewater (clarifier)"
      }
    ],
    "leases": [],
    "checklist": []
  },
  "Vincent": {
    "type": "Operations Yard",
    "swis": "",
    "addr": "5355 Vincent Ave",
    "city": "Irwindale",
    "lat": 34.085,
    "lng": -117.953,
    "folder": "https://caiwoodgroup-my.sharepoint.com/personal/tamer_hassanein_caiwoodgroup_com/Documents/Athens/Environmental Facility Permits - Documents/Vincent",
    "siteMap": "https://caiwoodgroup-my.sharepoint.com/personal/tamer_hassanein_caiwoodgroup_com/Documents/Athens/Facilities Site Plan - Facilities/Vincent/2023 Stormwater Site Map Vincent.pdf",
    "permits": [
      {
        "id": "p-vincent-01",
        "name": "Industrial Stormwater (IGP)",
        "agency": "State Water Resources Control Board (LA RWQCB)",
        "number": "WDID 4 19I021980",
        "status": "active",
        "expires": null,
        "cycle": "",
        "area": "Stormwater",
        "doc": "https://caiwoodgroup-my.sharepoint.com/personal/tamer_hassanein_caiwoodgroup_com/Documents/Athens/Environmental Facility Permits - Documents/Vincent/Stormwater"
      },
      {
        "id": "p-vincent-02",
        "name": "Hazardous Materials Business Plan (CUPA)",
        "agency": "CUPA",
        "number": "",
        "status": "verify",
        "expires": null,
        "cycle": "",
        "area": "CUPA",
        "doc": "https://caiwoodgroup-my.sharepoint.com/personal/tamer_hassanein_caiwoodgroup_com/Documents/Athens/Environmental Facility Permits - Documents/Vincent/CUPA haz mat"
      },
      {
        "id": "p-vincent-03",
        "name": "SPCC Plan",
        "agency": "US EPA (self-certified)",
        "number": "",
        "status": "verify",
        "expires": null,
        "cycle": "",
        "area": "SPCC",
        "doc": "https://caiwoodgroup-my.sharepoint.com/personal/tamer_hassanein_caiwoodgroup_com/Documents/Athens/Environmental Facility Permits - Documents/Vincent/SPCC oil spill"
      },
      {
        "id": "p-vincent-04",
        "name": "Waste Discharge Requirements (WDR)",
        "agency": "LA RWQCB",
        "number": "",
        "status": "verify",
        "expires": null,
        "cycle": "",
        "area": "Wastewater (clarifier)",
        "doc": "https://caiwoodgroup-my.sharepoint.com/personal/tamer_hassanein_caiwoodgroup_com/Documents/Athens/Environmental Facility Permits - Documents/Vincent/Wastewater (clarifier)"
      }
    ],
    "leases": [],
    "checklist": []
  },
  "SVMRF": {
    "type": "Materials Recovery Facility",
    "swis": "",
    "addr": "11121 Pendleton Avenue",
    "city": "Sun Valley",
    "lat": 34.245,
    "lng": -118.388,
    "folder": "https://caiwoodgroup-my.sharepoint.com/personal/tamer_hassanein_caiwoodgroup_com/Documents/Athens/Environmental Facility Permits - Documents/SVMRF",
    "permits": [
      {
        "id": "p-svmrf-01",
        "name": "Solid Waste Facility Permit",
        "agency": "CalRecycle / LEA",
        "number": "",
        "status": "verify",
        "expires": null,
        "cycle": "5-year review",
        "area": "SWFP",
        "doc": "https://caiwoodgroup-my.sharepoint.com/personal/tamer_hassanein_caiwoodgroup_com/Documents/Athens/Environmental Facility Permits - Documents/SVMRF/SWFP"
      },
      {
        "id": "p-svmrf-02",
        "name": "Industrial Stormwater (IGP)",
        "agency": "State Water Resources Control Board (RWQCB)",
        "number": "WDID 4 19I025193",
        "status": "active",
        "expires": null,
        "cycle": "annual",
        "area": "Stormwater",
        "doc": "https://caiwoodgroup-my.sharepoint.com/personal/tamer_hassanein_caiwoodgroup_com/Documents/Athens/Environmental Facility Permits - Documents/SVMRF/Stormwater (includes Peoria)"
      },
      {
        "id": "p-svmrf-03",
        "name": "Hazardous Materials Business Plan (CUPA)",
        "agency": "CUPA",
        "number": "",
        "status": "verify",
        "expires": null,
        "cycle": "annual (2025-2026)",
        "area": "CUPA",
        "doc": "https://caiwoodgroup-my.sharepoint.com/personal/tamer_hassanein_caiwoodgroup_com/Documents/Athens/Environmental Facility Permits - Documents/SVMRF/CUPA haz mat"
      },
      {
        "id": "p-svmrf-04",
        "name": "EPA ID (Hazardous Waste Generator)",
        "agency": "US EPA / CA DTSC",
        "number": "CAL000234960",
        "status": "active",
        "expires": null,
        "cycle": "",
        "area": "EPA ID",
        "doc": "https://caiwoodgroup-my.sharepoint.com/personal/tamer_hassanein_caiwoodgroup_com/Documents/Athens/Environmental Facility Permits - Documents/SVMRF/EPA ID"
      },
      {
        "id": "p-svmrf-05",
        "name": "Air Permit — Baghouse",
        "agency": "South Coast AQMD",
        "number": "G45985",
        "status": "active",
        "expires": null,
        "cycle": "",
        "area": "Air Permits",
        "doc": "https://caiwoodgroup-my.sharepoint.com/personal/tamer_hassanein_caiwoodgroup_com/Documents/Athens/Environmental Facility Permits - Documents/SVMRF/Air Permits"
      },
      {
        "id": "p-svmrf-06",
        "name": "Air Permit — Portable Equipment (CARB PERP)",
        "agency": "CARB PERP",
        "number": "168448",
        "status": "active",
        "expires": "2027-05-31",
        "cycle": "",
        "area": "Air Permits",
        "doc": "https://caiwoodgroup-my.sharepoint.com/personal/tamer_hassanein_caiwoodgroup_com/Documents/Athens/Environmental Facility Permits - Documents/SVMRF/Air Permits"
      },
      {
        "id": "p-svmrf-07",
        "name": "SPCC Plan",
        "agency": "US EPA (self-certified)",
        "number": "",
        "status": "active",
        "expires": null,
        "cycle": "5-year review",
        "area": "SPCC",
        "doc": "https://caiwoodgroup-my.sharepoint.com/personal/tamer_hassanein_caiwoodgroup_com/Documents/Athens/Environmental Facility Permits - Documents/SVMRF/SPCC oil spill"
      },
      {
        "id": "p-svmrf-08",
        "name": "Waste Discharge Requirements (WDR)",
        "agency": "RWQCB",
        "number": "",
        "status": "verify",
        "expires": null,
        "cycle": "",
        "area": "Wastewater (clarifier)",
        "doc": "https://caiwoodgroup-my.sharepoint.com/personal/tamer_hassanein_caiwoodgroup_com/Documents/Athens/Environmental Facility Permits - Documents/SVMRF/Wastewater (clarifier)"
      },
      {
        "id": "p-svmrf-09",
        "name": "Conditional Use Permit (Land Use)",
        "agency": "City of Los Angeles (Zoning Administrator)",
        "number": "ZA-98-0427-CUZ-PA3",
        "status": "active",
        "expires": null,
        "cycle": "",
        "area": "CUP land use",
        "doc": "https://caiwoodgroup-my.sharepoint.com/personal/tamer_hassanein_caiwoodgroup_com/Documents/Athens/Environmental Facility Permits - Documents/SVMRF/CUP land use"
      },
      {
        "id": "p-svmrf-10",
        "name": "CalRecycle Waste Tire Program",
        "agency": "CalRecycle",
        "number": "TPID 1954111-01",
        "status": "active",
        "expires": null,
        "cycle": "",
        "area": "Waste Tire",
        "doc": "https://caiwoodgroup-my.sharepoint.com/personal/tamer_hassanein_caiwoodgroup_com/Documents/Athens/Environmental Facility Permits - Documents/SVMRF/CalRecycle Wastetire"
      },
      {
        "id": "p-svmrf-11",
        "name": "CDFA Weighmaster License",
        "agency": "CDFA Division of Measurement Standards",
        "number": "",
        "status": "active",
        "expires": "2026-09-01",
        "cycle": "annual",
        "area": "CDFA Weighmaster",
        "doc": "https://caiwoodgroup-my.sharepoint.com/personal/tamer_hassanein_caiwoodgroup_com/Documents/Athens/Environmental Facility Permits - Documents/SVMRF/CDFA Weighmaster"
      }
    ],
    "leases": [],
    "checklist": []
  }
}
